alissonSomav1/__init__.py
alissonSomav1/somav2.py
alissonSomav1-0.1.dist-info/LICENSE
alissonSomav1-0.1.dist-info/METADATA
alissonSomav1-0.1.dist-info/WHEEL
alissonSomav1-0.1.dist-info/top_level.txt
alissonSomav1-0.1.dist-info/RECORD
